astocktrade/__init__.py
astocktrade/getdata.py
astocktrade/macal.py
astocktrade/upcal.py
astocktrade-0.0.8.dist-info/LICENSE
astocktrade-0.0.8.dist-info/METADATA
astocktrade-0.0.8.dist-info/WHEEL
astocktrade-0.0.8.dist-info/top_level.txt
astocktrade-0.0.8.dist-info/RECORD
