Metadata-Version: 2.1
Name: astocktrade
Version: 0.0.8
Summary: some tools for astocktrade
Home-page: https://github.com/laishuhan/astocktrade
Author: laishuhan
Author-email: 3027826050@qq.com
Classifier: Programming Language :: Python :: 3
Classifier: License :: OSI Approved :: MIT License
Classifier: Operating System :: OS Independent
License-File: LICENSE
